network_as_code-8.0.0.dist-info/METADATA
network_as_code-8.0.0.dist-info/WHEEL
network_as_code-8.0.0.dist-info/entry_points.txt
network_as_code-8.0.0.dist-info/licenses/LICENSE
network_as_code/__init__.py
network_as_code/api/__init__.py
network_as_code/api/authorization_api.py
network_as_code/api/call_forwarding_api.py
network_as_code/api/client.py
network_as_code/api/congestion_api.py
network_as_code/api/credentials_api.py
network_as_code/api/device_status_api.py
network_as_code/api/device_swap_api.py
network_as_code/api/geofencing_api.py
network_as_code/api/kyc_api.py
network_as_code/api/location_api.py
network_as_code/api/number_verification_api.py
network_as_code/api/qod_api.py
network_as_code/api/sim_swap_api.py
network_as_code/api/slice_api.py
network_as_code/api/utils.py
network_as_code/client.py
network_as_code/errors/__init__.py
network_as_code/errors/error_handler.py
network_as_code/models/__init__.py
network_as_code/models/authorization.py
network_as_code/models/congestion.py
network_as_code/models/device.py
network_as_code/models/device_status.py
network_as_code/models/geofencing.py
network_as_code/models/kyc_age.py
network_as_code/models/kyc_fill.py
network_as_code/models/kyc_match.py
network_as_code/models/kyc_tenure.py
network_as_code/models/location.py
network_as_code/models/session.py
network_as_code/models/slice.py
network_as_code/namespaces/__init__.py
network_as_code/namespaces/authorization.py
network_as_code/namespaces/device.py
network_as_code/namespaces/device_status.py
network_as_code/namespaces/geofencing.py
network_as_code/namespaces/insights.py
network_as_code/namespaces/kyc.py
network_as_code/namespaces/namespace.py
network_as_code/namespaces/session.py
network_as_code/namespaces/slice.py
network_as_code-8.0.0.dist-info/RECORD
