Metadata-Version: 2.1
Name: network_as_code
Version: 8.0.0
Author-Email: Sami Lahtinen <sami.lahtinen@nokia.com>, Pavel Garmuyev <pavel.garmuyev@nokia.com>
License: Apache-2.0
Requires-Python: <4.0,>=3.11
Requires-Dist: pydantic[email]<3.0.0,>=2.7.1
Requires-Dist: httpx<1.0.0,>=0.27.0
Requires-Dist: pip==25.3
Requires-Dist: urllib3>=2.6.0
Requires-Dist: filelock>=3.20.1
